Metadata-Version: 1.1
Name: zipcodetw
Version: 0.6.8
Summary: Find Taiwan ZIP code by address fuzzily.
Home-page: https://github.com/moskytw/zipcodetw
Author: Mosky
Author-email: mosky.tw@gmail.com
License: MIT
Platform: any
Classifier: Development Status :: 5 - Production/Stable
Classifier: Environment :: Console
Classifier: Intended Audience :: Developers
Classifier: License :: OSI Approved :: MIT License
Classifier: Operating System :: OS Independent
Classifier: Programming Language :: Python
Classifier: Programming Language :: Python :: 2.6
Classifier: Programming Language :: Python :: 2.7
Classifier: Programming Language :: Python :: 3
Classifier: Programming Language :: Python :: 3.5
Classifier: Programming Language :: Python :: 3.6
Classifier: Topic :: Utilities
Classifier: Topic :: Software Development :: Libraries :: Python Modules
